README.md
setup.py
shabbirlibrary/__init__.py
shabbirlibrary/operation.py
shabbirlibrary345678.egg-info/PKG-INFO
shabbirlibrary345678.egg-info/SOURCES.txt
shabbirlibrary345678.egg-info/dependency_links.txt
shabbirlibrary345678.egg-info/not-zip-safe
shabbirlibrary345678.egg-info/top_level.txt